{
  "$schema": "https://json.schemastore.org/dotnetcli.host",
  "symbolInfo": {
    "AzureSpringCloudHostingOption": {
      "longName": "azure-spring-cloud",
      "shortName": ""
    },
    "CloudConfigOption": {
      "longName": "cloud-config",
      "shortName": ""
    },
    "CloudFoundryHostingOption": {
      "longName": "cloud-foundry",
      "shortName": ""
    },
    "DescriptionOption": {
      "longName": "description",
      "shortName": "D"
    },
    "DockerOption": {
      "longName": "docker",
      "shortName": ""
    },
    "DynamicLoggerOption": {
      "longName": "dynamic-logger",
      "shortName": ""
    },
    "EurekaOption": {
      "longName": "eureka",
      "shortName": ""
    },
    "Framework": {
      "longName": "framework"
    },
    "HystrixOption": {
      "longName": "hystrix",
      "shortName": ""
    },
    "ManagementEndpointsOption": {
      "longName": "management-endpoints",
      "shortName": ""
    },
    "MessagingRabbitMqOption": {
      "longName": "messaging-rabbitmq",
      "shortName": ""
    },
    "MongoDbOption": {
      "longName": "mongodb",
      "shortName": ""
    },
    "MySqlEfCoreOption": {
      "longName": "mysql-efcore",
      "shortName": ""
    },
    "MySqlOption": {
      "longName": "mysql",
      "shortName": ""
    },
    "OAuthOption": {
      "longName": "oauth",
      "shortName": ""
    },
    "PlaceholderOption": {
      "longName": "placeholder",
      "shortName": ""
    },
    "PostgreSqlEfCoreOption": {
      "longName": "postgresql-efcore",
      "shortName": ""
    },
    "PostgreSqlOption": {
      "longName": "postgresql",
      "shortName": ""
    },
    "RabbitMqOption": {
      "longName": "rabbitmq",
      "shortName": ""
    },
    "RandomValueOption": {
      "longName": "random-value",
      "shortName": ""
    },
    "RedisOption": {
      "longName": "redis",
      "shortName": ""
    },
    "SkipRestoreOption": {
      "longName": "no-restore",
      "shortName": ""
    },
    "SqlServerOption": {
      "longName": "sqlserver",
      "shortName": ""
    },
    "SteeltoeVersionOption": {
      "longName": "steeltoe"
    }
  }
}
